imagehelpers/__init__.py
imagehelpers/image.py
image_helpers-0.1.4.dist-info/METADATA
image_helpers-0.1.4.dist-info/WHEEL
image_helpers-0.1.4.dist-info/top_level.txt
image_helpers-0.1.4.dist-info/RECORD
