Metadata-Version: 2.1
Name: image-helpers
Version: 0.1.4
Summary: Pacote para manipulacao de imagens
Home-page: UNKNOWN
Author: Gustavo Schaedler
Author-email: gustavopoa@gmail.com
License: MIT
Keywords: python image resize resizing thumbnail
Platform: UNKNOWN
Classifier: Topic :: Software Development :: Libraries :: Python Modules
Classifier: License :: OSI Approved :: MIT License
Classifier: Programming Language :: Python :: 3
Classifier: Programming Language :: Python :: 3.4
Classifier: Programming Language :: Python :: 3.5
Classifier: Programming Language :: Python :: 3.6
Classifier: Programming Language :: Python :: 3.7
Classifier: Programming Language :: Python :: 3.8
Classifier: Programming Language :: Python :: 3.9
Requires-Dist: Pillow (>=8.1.0)
Requires-Dist: requests (>=2.25.0)
